{
  "Name": "81 [THD]异形楼阁佐特塔 ",
  "AllSteps": [
    {
      "Remark": "",
      "TargetPos": {
        "X": -0.08944305,
        "Y": -478.0542,
        "Z": 185.75195
      },
      "IgnoreBattleState": false,
      "ArriveActionType": 6,
      "ArriveActionData": {
        "$type": "Trust.DungeonController.Dungeon.ArriveStepAction_WaitForNpc, Trust",
        "TimeOut": 15.0
      },
      "ReverseDir": false,
      "ExDistance": 0.0
    },
    {
      "Remark": "",
      "TargetPos": {
        "X": -1.0263122,
        "Y": -478.03632,
        "Z": 179.21378
      },
      "IgnoreBattleState": false,
      "ArriveActionType": 2,
      "ArriveActionData": {
        "$type": "Trust.DungeonController.Dungeon.ArriveStepAction_BattleWithMonster, Trust",
        "WaitTimeInSec": 3.0
      },
      "ReverseDir": false,
      "ExDistance": 0.0
    },
    {
      "Remark": "",
      "TargetPos": {
        "X": -6.841365,
        "Y": -470.4282,
        "Z": 114.743614
      },
      "IgnoreBattleState": false,
      "ArriveActionType": 6,
      "ArriveActionData": {
        "$type": "Trust.DungeonController.Dungeon.ArriveStepAction_WaitForNpc, Trust",
        "TimeOut": 15.0
      },
      "ReverseDir": false,
      "ExDistance": 0.0
    },
    {
      "Remark": "",
      "TargetPos": {
        "X": -12.855442,
        "Y": -469.80008,
        "Z": 107.82018
      },
      "IgnoreBattleState": false,
      "ArriveActionType": 2,
      "ArriveActionData": {
        "$type": "Trust.DungeonController.Dungeon.ArriveStepAction_BattleWithMonster, Trust",
        "WaitTimeInSec": 3.0
      },
      "ReverseDir": false,
      "ExDistance": 0.0
    },
    {
      "Remark": "",
      "TargetPos": {
        "X": -0.23779678,
        "Y": -465.78528,
        "Z": 39.121887
      },
      "IgnoreBattleState": false,
      "ArriveActionType": 6,
      "ArriveActionData": {
        "$type": "Trust.DungeonController.Dungeon.ArriveStepAction_WaitForNpc, Trust",
        "TimeOut": 15.0
      },
      "ReverseDir": false,
      "ExDistance": 0.0
    },
    {
      "Remark": "",
      "TargetPos": {
        "X": 47.64419,
        "Y": -460.70377,
        "Z": -1.9074109
      },
      "IgnoreBattleState": false,
      "ArriveActionType": 6,
      "ArriveActionData": {
        "$type": "Trust.DungeonController.Dungeon.ArriveStepAction_WaitForNpc, Trust",
        "TimeOut": 15.0
      },
      "ReverseDir": false,
      "ExDistance": 0.0
    },
    {
      "Remark": "",
      "TargetPos": {
        "X": 55.414047,
        "Y": -460.41455,
        "Z": -1.7709897
      },
      "IgnoreBattleState": false,
      "ArriveActionType": 2,
      "ArriveActionData": {
        "$type": "Trust.DungeonController.Dungeon.ArriveStepAction_BattleWithMonster, Trust",
        "WaitTimeInSec": 3.0
      },
      "ReverseDir": false,
      "ExDistance": 0.0
    },
    {
      "Remark": "",
      "TargetPos": {
        "X": 82.23106,
        "Y": -444.1559,
        "Z": -39.69324
      },
      "IgnoreBattleState": false,
      "ArriveActionType": 6,
      "ArriveActionData": {
        "$type": "Trust.DungeonController.Dungeon.ArriveStepAction_WaitForNpc, Trust",
        "TimeOut": 15.0
      },
      "ReverseDir": false,
      "ExDistance": 0.0
    },
    {
      "Remark": "",
      "TargetPos": {
        "X": 72.48094,
        "Y": -444.1718,
        "Z": -42.54689
      },
      "IgnoreBattleState": false,
      "ArriveActionType": 2,
      "ArriveActionData": {
        "$type": "Trust.DungeonController.Dungeon.ArriveStepAction_BattleWithMonster, Trust",
        "WaitTimeInSec": 3.0
      },
      "ReverseDir": false,
      "ExDistance": 0.0
    },
    {
      "Remark": "",
      "TargetPos": {
        "X": 67.97333,
        "Y": -443.0066,
        "Z": -102.189384
      },
      "IgnoreBattleState": false,
      "ArriveActionType": 6,
      "ArriveActionData": {
        "$type": "Trust.DungeonController.Dungeon.ArriveStepAction_WaitForNpc, Trust",
        "TimeOut": 15.0
      },
      "ReverseDir": false,
      "ExDistance": 0.0
    },
    {
      "Remark": "",
      "TargetPos": {
        "X": 68.19629,
        "Y": -442.96777,
        "Z": -129.3653
      },
      "IgnoreBattleState": false,
      "ArriveActionType": 5,
      "ArriveActionData": {
        "$type": "Trust.DungeonController.Dungeon.ArriveStepAction_AgainstBoss, Trust",
        "BossAreas": [
          {
            "Remark": "",
            "AreaShapeType": 0,
            "AreaShape": {
              "$type": "AEAssist.Avoid.CircleShape, AEAssist",
              "Radius": 19.499998,
              "Origin": {
                "X": 68.12863,
                "Y": -442.96777,
                "Z": -124.02276
              },
              "Name": null
            }
          }
        ],
        "WaitTimeInSec": 10.0,
        "BossIndex": 0
      },
      "ReverseDir": false,
      "ExDistance": 0.0
    },
    {
      "Remark": "",
      "TargetPos": {
        "X": -299.51422,
        "Y": -184.71344,
        "Z": 201.88348
      },
      "IgnoreBattleState": false,
      "ArriveActionType": 6,
      "ArriveActionData": {
        "$type": "Trust.DungeonController.Dungeon.ArriveStepAction_WaitForNpc, Trust",
        "TimeOut": 15.0
      },
      "ReverseDir": false,
      "ExDistance": 0.0
    },
    {
      "Remark": "",
      "TargetPos": {
        "X": -301.54068,
        "Y": -185.07335,
        "Z": 188.9371
      },
      "IgnoreBattleState": false,
      "ArriveActionType": 2,
      "ArriveActionData": {
        "$type": "Trust.DungeonController.Dungeon.ArriveStepAction_BattleWithMonster, Trust",
        "WaitTimeInSec": 3.0
      },
      "ReverseDir": false,
      "ExDistance": 0.0
    },
    {
      "Remark": "",
      "TargetPos": {
        "X": -301.38553,
        "Y": -184.79904,
        "Z": 155.33714
      },
      "IgnoreBattleState": false,
      "ArriveActionType": 6,
      "ArriveActionData": {
        "$type": "Trust.DungeonController.Dungeon.ArriveStepAction_WaitForNpc, Trust",
        "TimeOut": 15.0
      },
      "ReverseDir": false,
      "ExDistance": 0.0
    },
    {
      "Remark": "",
      "TargetPos": {
        "X": -306.61417,
        "Y": -184.71338,
        "Z": 139.58014
      },
      "IgnoreBattleState": false,
      "ArriveActionType": 2,
      "ArriveActionData": {
        "$type": "Trust.DungeonController.Dungeon.ArriveStepAction_BattleWithMonster, Trust",
        "WaitTimeInSec": 3.0
      },
      "ReverseDir": false,
      "ExDistance": 0.0
    },
    {
      "Remark": "",
      "TargetPos": {
        "X": -327.80627,
        "Y": -180.68452,
        "Z": 110.44431
      },
      "IgnoreBattleState": false,
      "ArriveActionType": 6,
      "ArriveActionData": {
        "$type": "Trust.DungeonController.Dungeon.ArriveStepAction_WaitForNpc, Trust",
        "TimeOut": 15.0
      },
      "ReverseDir": false,
      "ExDistance": 0.0
    },
    {
      "Remark": "",
      "TargetPos": {
        "X": -334.73773,
        "Y": -181.02016,
        "Z": 101.60907
      },
      "IgnoreBattleState": false,
      "ArriveActionType": 2,
      "ArriveActionData": {
        "$type": "Trust.DungeonController.Dungeon.ArriveStepAction_BattleWithMonster, Trust",
        "WaitTimeInSec": 3.0
      },
      "ReverseDir": false,
      "ExDistance": 0.0
    },
    {
      "Remark": "",
      "TargetPos": {
        "X": -317.5662,
        "Y": -180.89055,
        "Z": 76.82236
      },
      "IgnoreBattleState": false,
      "ArriveActionType": 6,
      "ArriveActionData": {
        "$type": "Trust.DungeonController.Dungeon.ArriveStepAction_WaitForNpc, Trust",
        "TimeOut": 15.0
      },
      "ReverseDir": false,
      "ExDistance": 0.0
    },
    {
      "Remark": "",
      "TargetPos": {
        "X": -303.95474,
        "Y": -179.5299,
        "Z": 73.764145
      },
      "IgnoreBattleState": false,
      "ArriveActionType": 2,
      "ArriveActionData": {
        "$type": "Trust.DungeonController.Dungeon.ArriveStepAction_BattleWithMonster, Trust",
        "WaitTimeInSec": 3.0
      },
      "ReverseDir": false,
      "ExDistance": 0.0
    },
    {
      "Remark": "",
      "TargetPos": {
        "X": -262.1367,
        "Y": -171.76393,
        "Z": 78.78943
      },
      "IgnoreBattleState": false,
      "ArriveActionType": 6,
      "ArriveActionData": {
        "$type": "Trust.DungeonController.Dungeon.ArriveStepAction_WaitForNpc, Trust",
        "TimeOut": 15.0
      },
      "ReverseDir": false,
      "ExDistance": 0.0
    },
    {
      "Remark": "",
      "TargetPos": {
        "X": -250.68712,
        "Y": -172.03445,
        "Z": 77.962296
      },
      "IgnoreBattleState": false,
      "ArriveActionType": 2,
      "ArriveActionData": {
        "$type": "Trust.DungeonController.Dungeon.ArriveStepAction_BattleWithMonster, Trust",
        "WaitTimeInSec": 3.0
      },
      "ReverseDir": false,
      "ExDistance": 0.0
    },
    {
      "Remark": "",
      "TargetPos": {
        "X": -258.81198,
        "Y": -169.00002,
        "Z": -10.009194
      },
      "IgnoreBattleState": false,
      "ArriveActionType": 6,
      "ArriveActionData": {
        "$type": "Trust.DungeonController.Dungeon.ArriveStepAction_WaitForNpc, Trust",
        "TimeOut": 15.0
      },
      "ReverseDir": false,
      "ExDistance": 0.0
    },
    {
      "Remark": "",
      "TargetPos": {
        "X": -258.2701,
        "Y": -169.0,
        "Z": -23.632242
      },
      "IgnoreBattleState": false,
      "ArriveActionType": 5,
      "ArriveActionData": {
        "$type": "Trust.DungeonController.Dungeon.ArriveStepAction_AgainstBoss, Trust",
        "BossAreas": [
          {
            "Remark": "",
            "AreaShapeType": 0,
            "AreaShape": {
              "$type": "AEAssist.Avoid.CircleShape, AEAssist",
              "Radius": 19.499998,
              "Origin": {
                "X": -258.08273,
                "Y": -169.00002,
                "Z": -25.968184
              },
              "Name": null
            }
          }
        ],
        "WaitTimeInSec": 10.0,
        "BossIndex": 1
      },
      "ReverseDir": false,
      "ExDistance": 0.0
    },
    {
      "Remark": "",
      "TargetPos": {
        "X": 0.29716,
        "Y": 536.1677,
        "Z": 26.047873
      },
      "IgnoreBattleState": false,
      "ArriveActionType": 6,
      "ArriveActionData": {
        "$type": "Trust.DungeonController.Dungeon.ArriveStepAction_WaitForNpc, Trust",
        "TimeOut": 15.0
      },
      "ReverseDir": false,
      "ExDistance": 0.0
    },
    {
      "Remark": "",
      "TargetPos": {
        "X": 0.08283231,
        "Y": 534.84204,
        "Z": 13.775129
      },
      "IgnoreBattleState": false,
      "ArriveActionType": 2,
      "ArriveActionData": {
        "$type": "Trust.DungeonController.Dungeon.ArriveStepAction_BattleWithMonster, Trust",
        "WaitTimeInSec": 3.0
      },
      "ReverseDir": false,
      "ExDistance": 0.0
    },
    {
      "Remark": "",
      "TargetPos": {
        "X": 15.8225975,
        "Y": 534.6429,
        "Z": -13.41395
      },
      "IgnoreBattleState": false,
      "ArriveActionType": 6,
      "ArriveActionData": {
        "$type": "Trust.DungeonController.Dungeon.ArriveStepAction_WaitForNpc, Trust",
        "TimeOut": 15.0
      },
      "ReverseDir": false,
      "ExDistance": 0.0
    },
    {
      "Remark": "",
      "TargetPos": {
        "X": 22.336044,
        "Y": 534.9061,
        "Z": -21.92502
      },
      "IgnoreBattleState": false,
      "ArriveActionType": 2,
      "ArriveActionData": {
        "$type": "Trust.DungeonController.Dungeon.ArriveStepAction_BattleWithMonster, Trust",
        "WaitTimeInSec": 3.0
      },
      "ReverseDir": false,
      "ExDistance": 0.0
    },
    {
      "Remark": "",
      "TargetPos": {
        "X": 48.182514,
        "Y": 535.10565,
        "Z": -46.910286
      },
      "IgnoreBattleState": false,
      "ArriveActionType": 6,
      "ArriveActionData": {
        "$type": "Trust.DungeonController.Dungeon.ArriveStepAction_WaitForNpc, Trust",
        "TimeOut": 15.0
      },
      "ReverseDir": false,
      "ExDistance": 0.0
    },
    {
      "Remark": "",
      "TargetPos": {
        "X": 52.735725,
        "Y": 534.9511,
        "Z": -51.73196
      },
      "IgnoreBattleState": false,
      "ArriveActionType": 2,
      "ArriveActionData": {
        "$type": "Trust.DungeonController.Dungeon.ArriveStepAction_BattleWithMonster, Trust",
        "WaitTimeInSec": 3.0
      },
      "ReverseDir": false,
      "ExDistance": 0.0
    },
    {
      "Remark": "",
      "TargetPos": {
        "X": 61.11772,
        "Y": 534.8545,
        "Z": -59.843277
      },
      "IgnoreBattleState": false,
      "ArriveActionType": 2,
      "ArriveActionData": {
        "$type": "Trust.DungeonController.Dungeon.ArriveStepAction_BattleWithMonster, Trust",
        "WaitTimeInSec": 3.0
      },
      "ReverseDir": false,
      "ExDistance": 0.0
    },
    {
      "Remark": "",
      "TargetPos": {
        "X": 1.5571246,
        "Y": 538.22894,
        "Z": -120.0623
      },
      "IgnoreBattleState": false,
      "ArriveActionType": 6,
      "ArriveActionData": {
        "$type": "Trust.DungeonController.Dungeon.ArriveStepAction_WaitForNpc, Trust",
        "TimeOut": 15.0
      },
      "ReverseDir": false,
      "ExDistance": 0.0
    },
    {
      "Remark": "",
      "TargetPos": {
        "X": -13.342811,
        "Y": 538.2792,
        "Z": -135.15247
      },
      "IgnoreBattleState": false,
      "ArriveActionType": 2,
      "ArriveActionData": {
        "$type": "Trust.DungeonController.Dungeon.ArriveStepAction_BattleWithMonster, Trust",
        "WaitTimeInSec": 3.0
      },
      "ReverseDir": false,
      "ExDistance": 0.0
    },
    {
      "Remark": "",
      "TargetPos": {
        "X": -23.478529,
        "Y": 538.4202,
        "Z": -127.30855
      },
      "IgnoreBattleState": false,
      "ArriveActionType": 2,
      "ArriveActionData": {
        "$type": "Trust.DungeonController.Dungeon.ArriveStepAction_BattleWithMonster, Trust",
        "WaitTimeInSec": 3.0
      },
      "ReverseDir": false,
      "ExDistance": 0.0
    },
    {
      "Remark": "",
      "TargetPos": {
        "X": -38.24153,
        "Y": 541.5877,
        "Z": -117.6365
      },
      "IgnoreBattleState": false,
      "ArriveActionType": 2,
      "ArriveActionData": {
        "$type": "Trust.DungeonController.Dungeon.ArriveStepAction_BattleWithMonster, Trust",
        "WaitTimeInSec": 3.0
      },
      "ReverseDir": false,
      "ExDistance": 0.0
    },
    {
      "Remark": "",
      "TargetPos": {
        "X": -51.086617,
        "Y": 544.1686,
        "Z": -104.83638
      },
      "IgnoreBattleState": false,
      "ArriveActionType": 2,
      "ArriveActionData": {
        "$type": "Trust.DungeonController.Dungeon.ArriveStepAction_BattleWithMonster, Trust",
        "WaitTimeInSec": 3.0
      },
      "ReverseDir": false,
      "ExDistance": 0.0
    },
    {
      "Remark": "",
      "TargetPos": {
        "X": -66.235985,
        "Y": 544.9415,
        "Z": -88.67882
      },
      "IgnoreBattleState": false,
      "ArriveActionType": 2,
      "ArriveActionData": {
        "$type": "Trust.DungeonController.Dungeon.ArriveStepAction_BattleWithMonster, Trust",
        "WaitTimeInSec": 3.0
      },
      "ReverseDir": false,
      "ExDistance": 0.0
    },
    {
      "Remark": "",
      "TargetPos": {
        "X": -87.63012,
        "Y": 541.70044,
        "Z": -68.92341
      },
      "IgnoreBattleState": false,
      "ArriveActionType": 6,
      "ArriveActionData": {
        "$type": "Trust.DungeonController.Dungeon.ArriveStepAction_WaitForNpc, Trust",
        "TimeOut": 15.0
      },
      "ReverseDir": false,
      "ExDistance": 0.0
    },
    {
      "Remark": "",
      "TargetPos": {
        "X": -93.616745,
        "Y": 541.6906,
        "Z": -62.736565
      },
      "IgnoreBattleState": false,
      "ArriveActionType": 2,
      "ArriveActionData": {
        "$type": "Trust.DungeonController.Dungeon.ArriveStepAction_BattleWithMonster, Trust",
        "WaitTimeInSec": 3.0
      },
      "ReverseDir": false,
      "ExDistance": 0.0
    },
    {
      "Remark": "",
      "TargetPos": {
        "X": -39.822586,
        "Y": 546.104,
        "Z": -38.097687
      },
      "IgnoreBattleState": false,
      "ArriveActionType": 6,
      "ArriveActionData": {
        "$type": "Trust.DungeonController.Dungeon.ArriveStepAction_WaitForNpc, Trust",
        "TimeOut": 15.0
      },
      "ReverseDir": false,
      "ExDistance": 0.0
    },
    {
      "Remark": "",
      "TargetPos": {
        "X": -31.4194,
        "Y": 546.104,
        "Z": -45.785263
      },
      "IgnoreBattleState": false,
      "ArriveActionType": 5,
      "ArriveActionData": {
        "$type": "Trust.DungeonController.Dungeon.ArriveStepAction_AgainstBoss, Trust",
        "BossAreas": [
          {
            "Remark": "",
            "AreaShapeType": 0,
            "AreaShape": {
              "$type": "AEAssist.Avoid.CircleShape, AEAssist",
              "Radius": 19.499998,
              "Origin": {
                "X": -27.408514,
                "Y": 546.104,
                "Z": -49.588383
              },
              "Name": null
            }
          }
        ],
        "WaitTimeInSec": 10.0,
        "BossIndex": 2
      },
      "ReverseDir": false,
      "ExDistance": 0.0
    }
  ],
  "EntryType": 1,
  "DutyId": 12,
  "TrustVersion": 1,
  "Index": 0,
  "BossTriggerLines": [
    {
      "Remark": "boss1",
      "Root": {
        "DisplayName": "Start",
        "Childs": [
          {
            "$type": "AEAssist.CombatRoutine.Trigger.Node.TreeLoop, AEAssist",
            "DisplayName": "循环 [99]次",
            "Times": 99,
            "Childs": [
              {
                "$type": "AEAssist.CombatRoutine.Trigger.Node.TreeClearWaitNode, AEAssist",
                "DisplayName": "清理等待条件",
                "GUID": "d7af668a-71fb-4f05-bbd4-bf1113e4a46d",
                "Important": false,
                "Color": {
                  "X": 1.0,
                  "Y": 1.0,
                  "Z": 0.4,
                  "W": 1.0
                },
                "Id": 3,
                "Enable": true,
                "Remark": "每次循环开始 都要清理之前添加的监听 防止旧状态产生影响"
              },
              {
                "$type": "AEAssist.CombatRoutine.Trigger.Node.TreeParallel, AEAssist",
                "DisplayName": "并行选择",
                "AnyReturn": true,
                "Childs": [
                  {
                    "$type": "Trust.DungeonController.SpellReaction.Trigger.TreeSpellResolver, Trust",
                    "SpellId": 25234,
                    "ResolverDatas": [
                      {
                        "ResolverType": 1,
                        "ExData": {
                          "$type": "Trust.DungeonController.SpellReaction.FollowNpcExData, Trust",
                          "DontFollowTank": false
                        },
                        "Remark": "",
                        "DelayInSec": 0.3,
                        "TimeInSec": 5.0
                      }
                    ],
                    "JobsLimit": 0,
                    "DisplayName": "机制应对:监听技能",
                    "GUID": "e62634ca-10a5-4f9b-8abd-d4c0204e8b11",
                    "Important": false,
                    "Color": {
                      "X": 1.0,
                      "Y": 1.0,
                      "Z": 0.4,
                      "W": 1.0
                    },
                    "Id": 5,
                    "Enable": true,
                    "Remark": "人趣冰封"
                  },
                  {
                    "$type": "Trust.DungeonController.SpellReaction.Trigger.TreeSpellResolver, Trust",
                    "SpellId": 25233,
                    "ResolverDatas": [
                      {
                        "ResolverType": 1,
                        "ExData": {
                          "$type": "Trust.DungeonController.SpellReaction.FollowNpcExData, Trust",
                          "DontFollowTank": false
                        },
                        "Remark": "",
                        "DelayInSec": 0.3,
                        "TimeInSec": 5.0
                      }
                    ],
                    "JobsLimit": 0,
                    "DisplayName": "机制应对:监听技能",
                    "GUID": "e62634ca-10a5-4f9b-8abd-d4c0204e8b11",
                    "Important": false,
                    "Color": {
                      "X": 1.0,
                      "Y": 1.0,
                      "Z": 0.4,
                      "W": 1.0
                    },
                    "Id": 6,
                    "Enable": true,
                    "Remark": "人趣爆炎"
                  },
                  {
                    "$type": "Trust.DungeonController.SpellReaction.Trigger.TreeSpellResolver, Trust",
                    "SpellId": 25240,
                    "ResolverDatas": [
                      {
                        "ResolverType": 1,
                        "ExData": {
                          "$type": "Trust.DungeonController.SpellReaction.FollowNpcExData, Trust",
                          "DontFollowTank": false
                        },
                        "Remark": "",
                        "DelayInSec": 0.3,
                        "TimeInSec": 5.0
                      }
                    ],
                    "JobsLimit": 0,
                    "DisplayName": "机制应对:监听技能",
                    "GUID": "51c20c27-f0d6-4d96-a211-4cb7082fa6af",
                    "Important": false,
                    "Color": {
                      "X": 1.0,
                      "Y": 1.0,
                      "Z": 0.4,
                      "W": 1.0
                    },
                    "Id": 7,
                    "Enable": true,
                    "Remark": "人趣剧毒菌"
                  },
                  {
                    "$type": "Trust.DungeonController.SpellReaction.Trigger.TreeSpellResolver, Trust",
                    "SpellId": 25371,
                    "ResolverDatas": [
                      {
                        "ResolverType": 1,
                        "ExData": {
                          "$type": "Trust.DungeonController.SpellReaction.FollowNpcExData, Trust",
                          "DontFollowTank": false
                        },
                        "Remark": "",
                        "DelayInSec": 12.0,
                        "TimeInSec": 5.0
                      }
                    ],
                    "JobsLimit": 0,
                    "DisplayName": "机制应对:监听技能",
                    "GUID": "51c20c27-f0d6-4d96-a211-4cb7082fa6af",
                    "Important": false,
                    "Color": {
                      "X": 1.0,
                      "Y": 1.0,
                      "Z": 0.4,
                      "W": 1.0
                    },
                    "Id": 8,
                    "Enable": true,
                    "Remark": "魔力操纵：冰封"
                  },
                  {
                    "$type": "Trust.DungeonController.SpellReaction.Trigger.TreeSpellResolver, Trust",
                    "SpellId": 25242,
                    "ResolverDatas": [
                      {
                        "ResolverType": 1,
                        "ExData": {
                          "$type": "Trust.DungeonController.SpellReaction.FollowNpcExData, Trust",
                          "DontFollowTank": false
                        },
                        "Remark": "",
                        "DelayInSec": 12.0,
                        "TimeInSec": 5.0
                      }
                    ],
                    "JobsLimit": 0,
                    "DisplayName": "机制应对:监听技能",
                    "GUID": "51c20c27-f0d6-4d96-a211-4cb7082fa6af",
                    "Important": false,
                    "Color": {
                      "X": 1.0,
                      "Y": 1.0,
                      "Z": 0.4,
                      "W": 1.0
                    },
                    "Id": 9,
                    "Enable": true,
                    "Remark": "魔力操纵：爆炎"
                  },
                  {
                    "$type": "Trust.DungeonController.SpellReaction.Trigger.TreeSpellResolver, Trust",
                    "SpellId": 25373,
                    "ResolverDatas": [
                      {
                        "ResolverType": 1,
                        "ExData": {
                          "$type": "Trust.DungeonController.SpellReaction.FollowNpcExData, Trust",
                          "DontFollowTank": false
                        },
                        "Remark": "",
                        "DelayInSec": 12.0,
                        "TimeInSec": 5.0
                      }
                    ],
                    "JobsLimit": 0,
                    "DisplayName": "机制应对:监听技能",
                    "GUID": "51c20c27-f0d6-4d96-a211-4cb7082fa6af",
                    "Important": false,
                    "Color": {
                      "X": 1.0,
                      "Y": 1.0,
                      "Z": 0.4,
                      "W": 1.0
                    },
                    "Id": 10,
                    "Enable": true,
                    "Remark": "魔力操纵：剧毒菌"
                  }
                ],
                "GUID": "b78b6758-86d4-4c6d-97fe-02081d4a7243",
                "Important": true,
                "Color": {
                  "X": 1.0,
                  "Y": 1.0,
                  "Z": 0.4,
                  "W": 1.0
                },
                "Id": 4,
                "Enable": true,
                "Remark": "[并行选择]下的子节点同时执行,触发添加技能监听.任意一个监听被触发后，本次循环结束"
              }
            ],
            "GUID": "0f228300-1770-492c-b9c3-9fce9253617c",
            "Important": false,
            "Color": {
              "X": 1.0,
              "Y": 1.0,
              "Z": 0.4,
              "W": 1.0
            },
            "Id": 2,
            "Enable": true,
            "Remark": "循环处理（因为一般副本boss的技能都是循环的）"
          }
        ],
        "GUID": "e4794b3e-6a40-4699-b4b2-59f8c38ee282",
        "Important": false,
        "Color": {
          "X": 1.0,
          "Y": 1.0,
          "Z": 0.4,
          "W": 1.0
        },
        "Id": 1,
        "Enable": true,
        "Remark": ""
      }
    },
    {
      "Remark": "boss2",
      "Root": {
        "DisplayName": "Start",
        "Childs": [
          {
            "$type": "AEAssist.CombatRoutine.Trigger.Node.TreeLoop, AEAssist",
            "DisplayName": "循环 [99]次",
            "Times": 99,
            "Childs": [
              {
                "$type": "AEAssist.CombatRoutine.Trigger.Node.TreeClearWaitNode, AEAssist",
                "DisplayName": "清理等待条件",
                "GUID": "c7a8d649-562e-487b-b227-4781926f1f8a",
                "Important": false,
                "Color": {
                  "X": 1.0,
                  "Y": 1.0,
                  "Z": 0.4,
                  "W": 1.0
                },
                "Id": 3,
                "Enable": true,
                "Remark": "每次循环开始 都要清理之前添加的监听 防止旧状态产生影响"
              },
              {
                "$type": "AEAssist.CombatRoutine.Trigger.Node.TreeParallel, AEAssist",
                "DisplayName": "并行选择",
                "AnyReturn": true,
                "Childs": [
                  {
                    "$type": "Trust.DungeonController.SpellReaction.Trigger.TreeSpellResolver, Trust",
                    "SpellId": 25250,
                    "ResolverDatas": [
                      {
                        "ResolverType": 1,
                        "ExData": {
                          "$type": "Trust.DungeonController.SpellReaction.FollowNpcExData, Trust",
                          "DontFollowTank": false
                        },
                        "Remark": "",
                        "DelayInSec": 0.3,
                        "TimeInSec": 7.0
                      }
                    ],
                    "JobsLimit": 0,
                    "DisplayName": "机制应对:监听技能",
                    "GUID": "d9a5ece7-250d-48df-bf1c-f279168e3216",
                    "Important": false,
                    "Color": {
                      "X": 1.0,
                      "Y": 1.0,
                      "Z": 0.4,
                      "W": 1.0
                    },
                    "Id": 5,
                    "Enable": true,
                    "Remark": "起爆"
                  }
                ],
                "GUID": "4301c354-52c2-4bec-b9d5-52769a73ccb9",
                "Important": true,
                "Color": {
                  "X": 1.0,
                  "Y": 1.0,
                  "Z": 0.4,
                  "W": 1.0
                },
                "Id": 4,
                "Enable": true,
                "Remark": "[并行选择]下的子节点同时执行,触发添加技能监听.任意一个监听被触发后，本次循环结束"
              }
            ],
            "GUID": "69e27a50-be3f-4817-a21e-8272f83bd260",
            "Important": false,
            "Color": {
              "X": 1.0,
              "Y": 1.0,
              "Z": 0.4,
              "W": 1.0
            },
            "Id": 2,
            "Enable": true,
            "Remark": "循环处理（因为一般副本boss的技能都是循环的）"
          }
        ],
        "GUID": "3dd6434b-9482-44de-b227-35f870e0578a",
        "Important": false,
        "Color": {
          "X": 1.0,
          "Y": 1.0,
          "Z": 0.4,
          "W": 1.0
        },
        "Id": 1,
        "Enable": true,
        "Remark": ""
      }
    },
    {
      "Remark": "boss3",
      "Root": {
        "DisplayName": "Start",
        "Childs": [
          {
            "$type": "AEAssist.CombatRoutine.Trigger.Node.TreeLoop, AEAssist",
            "DisplayName": "循环 [99]次",
            "Times": 99,
            "Childs": [
              {
                "$type": "AEAssist.CombatRoutine.Trigger.Node.TreeClearWaitNode, AEAssist",
                "DisplayName": "清理等待条件",
                "GUID": "cb038217-d955-40ce-8bec-775fe3f98b8a",
                "Important": false,
                "Color": {
                  "X": 1.0,
                  "Y": 1.0,
                  "Z": 0.4,
                  "W": 1.0
                },
                "Id": 3,
                "Enable": true,
                "Remark": "每次循环开始 都要清理之前添加的监听 防止旧状态产生影响"
              },
              {
                "$type": "AEAssist.CombatRoutine.Trigger.Node.TreeParallel, AEAssist",
                "DisplayName": "并行选择",
                "AnyReturn": true,
                "Childs": [
                  {
                    "$type": "Trust.DungeonController.SpellReaction.Trigger.TreeSpellResolver, Trust",
                    "SpellId": 25261,
                    "ResolverDatas": [
                      {
                        "ResolverType": 1,
                        "ExData": {
                          "$type": "Trust.DungeonController.SpellReaction.FollowNpcExData, Trust",
                          "DontFollowTank": false
                        },
                        "Remark": "",
                        "DelayInSec": 10.0,
                        "TimeInSec": 17.0
                      }
                    ],
                    "JobsLimit": 0,
                    "DisplayName": "机制应对:监听技能",
                    "GUID": "bfd8fac2-83ae-40ad-8521-8b572071938b",
                    "Important": false,
                    "Color": {
                      "X": 1.0,
                      "Y": 1.0,
                      "Z": 0.4,
                      "W": 1.0
                    },
                    "Id": 5,
                    "Enable": true,
                    "Remark": "冰三角攻击"
                  },
                  {
                    "$type": "Trust.DungeonController.SpellReaction.Trigger.TreeSpellResolver, Trust",
                    "SpellId": 25263,
                    "ResolverDatas": [
                      {
                        "ResolverType": 1,
                        "ExData": {
                          "$type": "Trust.DungeonController.SpellReaction.FollowNpcExData, Trust",
                          "DontFollowTank": false
                        },
                        "Remark": "",
                        "DelayInSec": 0.3,
                        "TimeInSec": 5.0
                      }
                    ],
                    "JobsLimit": 0,
                    "DisplayName": "机制应对:监听技能",
                    "GUID": "5dfef0a3-2e3f-4dd8-8ad9-36cd5048880a",
                    "Important": false,
                    "Color": {
                      "X": 1.0,
                      "Y": 1.0,
                      "Z": 0.4,
                      "W": 1.0
                    },
                    "Id": 6,
                    "Enable": true,
                    "Remark": "三角爆炎"
                  },
                  {
                    "$type": "Trust.DungeonController.SpellReaction.Trigger.TreeSpellResolver, Trust",
                    "SpellId": 25286,
                    "ResolverDatas": [
                      {
                        "ResolverType": 1,
                        "ExData": {
                          "$type": "Trust.DungeonController.SpellReaction.FollowNpcExData, Trust",
                          "DontFollowTank": false
                        },
                        "Remark": "",
                        "DelayInSec": 0.2,
                        "TimeInSec": 5.0
                      }
                    ],
                    "JobsLimit": 0,
                    "DisplayName": "机制应对:监听技能",
                    "GUID": "5dfef0a3-2e3f-4dd8-8ad9-36cd5048880a",
                    "Important": false,
                    "Color": {
                      "X": 1.0,
                      "Y": 1.0,
                      "Z": 0.4,
                      "W": 1.0
                    },
                    "Id": 7,
                    "Enable": true,
                    "Remark": "人趣冰封"
                  },
                  {
                    "$type": "Trust.DungeonController.SpellReaction.Trigger.TreeSpellResolver, Trust",
                    "SpellId": 25286,
                    "ResolverDatas": [
                      {
                        "ResolverType": 1,
                        "ExData": {
                          "$type": "Trust.DungeonController.SpellReaction.FollowNpcExData, Trust",
                          "DontFollowTank": false
                        },
                        "Remark": "",
                        "DelayInSec": 10.0,
                        "TimeInSec": 17.0
                      }
                    ],
                    "JobsLimit": 0,
                    "DisplayName": "机制应对:监听技能",
                    "GUID": "5dfef0a3-2e3f-4dd8-8ad9-36cd5048880a",
                    "Important": false,
                    "Color": {
                      "X": 1.0,
                      "Y": 1.0,
                      "Z": 0.4,
                      "W": 1.0
                    },
                    "Id": 8,
                    "Enable": true,
                    "Remark": "火三角攻击"
                  },
                  {
                    "$type": "Trust.DungeonController.SpellReaction.Trigger.TreeSpellResolver, Trust",
                    "SpellId": 25277,
                    "ResolverDatas": [
                      {
                        "ResolverType": 1,
                        "ExData": {
                          "$type": "Trust.DungeonController.SpellReaction.FollowNpcExData, Trust",
                          "DontFollowTank": false
                        },
                        "Remark": "",
                        "DelayInSec": 0.3,
                        "TimeInSec": 8.0
                      }
                    ],
                    "JobsLimit": 0,
                    "DisplayName": "机制应对:监听技能",
                    "GUID": "5dfef0a3-2e3f-4dd8-8ad9-36cd5048880a",
                    "Important": false,
                    "Color": {
                      "X": 1.0,
                      "Y": 1.0,
                      "Z": 0.4,
                      "W": 1.0
                    },
                    "Id": 9,
                    "Enable": true,
                    "Remark": "起爆"
                  }
                ],
                "GUID": "35d702e6-f62f-4ab1-a2a7-fd9593998a5e",
                "Important": true,
                "Color": {
                  "X": 1.0,
                  "Y": 1.0,
                  "Z": 0.4,
                  "W": 1.0
                },
                "Id": 4,
                "Enable": true,
                "Remark": "[并行选择]下的子节点同时执行,触发添加技能监听.任意一个监听被触发后，本次循环结束"
              }
            ],
            "GUID": "188c531d-41a5-4120-8c36-f04804c44d2c",
            "Important": false,
            "Color": {
              "X": 1.0,
              "Y": 1.0,
              "Z": 0.4,
              "W": 1.0
            },
            "Id": 2,
            "Enable": true,
            "Remark": "循环处理（因为一般副本boss的技能都是循环的）"
          }
        ],
        "GUID": "a37f6cb9-55d0-4e78-815e-003cc80f1ae0",
        "Important": false,
        "Color": {
          "X": 1.0,
          "Y": 1.0,
          "Z": 0.4,
          "W": 1.0
        },
        "Id": 1,
        "Enable": true,
        "Remark": ""
      }
    }
  ],
  "MonsterSpellNeedAvoidList": [
    {
      "SpellId": 24140,
      "Remark": "左臂斩击"
    },
    {
      "SpellId": 24145,
      "Remark": "猛冲"
    },
    {
      "SpellId": 24138,
      "Remark": "魔导汽油弹"
    }
  ],
  "NeedIgnoreWhenAutoAddDangerArea": [],
  "Remark": "",
  "TerritoryTypeId": 952
}